dirtree/__init__.py
dirtree/__main__.py
dirtree/builder.py
dirtree-0.3.0.dev0.dist-info/DESCRIPTION.rst
dirtree-0.3.0.dev0.dist-info/METADATA
dirtree-0.3.0.dev0.dist-info/RECORD
dirtree-0.3.0.dev0.dist-info/WHEEL
dirtree-0.3.0.dev0.dist-info/entry_points.txt
dirtree-0.3.0.dev0.dist-info/metadata.json
dirtree-0.3.0.dev0.dist-info/top_level.txt
