Metadata-Version: 2.0
Name: dirtree
Version: 0.3.0.dev0
Summary: Generates representations of directory trees.
Home-page: https://github.com/zesme/dirtree
Author: Lucas F Torroba Hennigen
Author-email: lucasfth@gmail.com
License: MIT
Platform: UNKNOWN
